{"cameraMode":{"drawMode":0,"name":"Shaded","section":"Shading Mode"},"sceneLighting":true,"audioPlay":false,"sceneViewState":{"showFog":true,"showMaterialUpdate":false,"showSkybox":true,"showFlares":true,"showImageEffects":true,"showParticleSystems":true},"in2DMode":false,"pivot":{"x":6.966763973236084,"y":2.6421189308166506,"z":-5.071805953979492},"rotation":{"x":0.2302854061126709,"y":0.032106272876262668,"z":-0.007602187339216471,"w":0.9725636839866638},"size":63.9363899230957,"orthographic":false}